{
"type": "FeatureCollection",
"name": "soiltreepit",
"crs": { "type": "name", "properties": { "name": "urn:ogc:def:crs:OGC:1.3:CRS84" } },
"features": [
{ "type": "Feature", "properties": { "waterbody": "Jamaica Bay and Tributaries", "community": "305", "gi_feature": null, "dep_cont_1": "1", "asset_id": "142209", "project_ty": "Onsite", "dep_contra": "GK26W5-02", "asset_widt": "0.0", "nearest_in": "Jamaica Ave & Richmond St", "asset_type": "Engineered Soil Tree Pit", "bbl": "3041020019", "sewer_type": "Combined", "outfall": "26W-005", "asset_x_co": "1018122.67352", "secondary": null, "status_gro": "Constructed", "tree_commo": null, "asset_leng": "0.0", "gi_id": "K065-01RGa", "assembly_d": "54", "tree_latin": null, "row_onsite": "Onsite", "status": "Constructed", "asset_area": "43.5", "asset_y_co": "189480.84321", "project_na": "P.S. 65 K", "city_counc": "37", "constructi": null, "street_add": "26 Richmond St", "borough": "Brooklyn", "construc_1": null }, "geometry": { "type": "Point", "coordinates": [ -73.877864167205288, 40.686693060016928 ] } },
{ "type": "Feature", "properties": { "waterbody": "Jamaica Bay and Tributaries", "community": "305", "gi_feature": null, "dep_cont_1": "1", "asset_id": "142226", "project_ty": "Onsite", "dep_contra": "GK26W5-01", "asset_widt": "0.0", "nearest_in": "Logan St & New Lots Ave", "asset_type": "Engineered Soil Tree Pit", "bbl": "3042780001", "sewer_type": "Combined", "outfall": "26W-005", "asset_x_co": "1019018.10686", "secondary": null, "status_gro": "Constructed", "tree_commo": null, "asset_leng": "0.0", "gi_id": "K218-02RGb", "assembly_d": "60", "tree_latin": null, "row_onsite": "Onsite", "status": "Constructed", "asset_area": "290.0", "asset_y_co": "183202.69876", "project_na": "J.H.S. 218 K", "city_counc": "42", "constructi": null, "street_add": "671 Logan St", "borough": "Brooklyn", "construc_1": null }, "geometry": { "type": "Point", "coordinates": [ -73.874667866523936, 40.669457518908509 ] } },
{ "type": "Feature", "properties": { "waterbody": "Gowanus Canal", "community": "302", "gi_feature": null, "dep_cont_1": "1", "asset_id": "142231", "project_ty": "Onsite", "dep_contra": "GKRH34-01", "asset_widt": "0.0", "nearest_in": "Dean St & Hoyt St", "asset_type": "Engineered Soil Tree Pit", "bbl": "3001880014", "sewer_type": "Combined", "outfall": "RH-034", "asset_x_co": "987396.81056", "secondary": null, "status_gro": "Constructed", "tree_commo": null, "asset_leng": "0.0", "gi_id": "K261-02RGa", "assembly_d": "52", "tree_latin": null, "row_onsite": "Onsite", "status": "Constructed", "asset_area": "1430.0", "asset_y_co": "189601.83071", "project_na": "P.S. 261 K", "city_counc": "33", "constructi": null, "street_add": "288 Pacific St", "borough": "Brooklyn", "construc_1": null }, "geometry": { "type": "Point", "coordinates": [ -73.98865337602733, 40.687089399006716 ] } },
{ "type": "Feature", "properties": { "waterbody": "Bronx River", "community": "206", "gi_feature": null, "dep_cont_1": "1", "asset_id": "142243", "project_ty": "Onsite", "dep_contra": "GXHP04-03", "asset_widt": "0.0", "nearest_in": "Oakland Pl & Prospect Ave", "asset_type": "Engineered Soil Tree Pit", "bbl": "2031090001", "sewer_type": "Combined", "outfall": "HP-004", "asset_x_co": "1015477.4418", "secondary": null, "status_gro": "Constructed", "tree_commo": null, "asset_leng": "0.0", "gi_id": "X300-01RGa", "assembly_d": "79", "tree_latin": null, "row_onsite": "Onsite", "status": "Constructed", "asset_area": "170.0", "asset_y_co": "247586.679", "project_na": "C.S. 300 X", "city_counc": "15", "constructi": null, "street_add": "2050 Prospect Ave", "borough": "Bronx", "construc_1": null }, "geometry": { "type": "Point", "coordinates": [ -73.88713220089366, 40.846188079571888 ] } }
]
}
